astrbot/__init__.py
astrbot/api/__init__.py
astrbot/api/all.py
astrbot/api/message_components.py
astrbot/api/event/__init__.py
astrbot/api/event/filter/__init__.py
astrbot/api/platform/__init__.py
astrbot/api/provider/__init__.py
astrbot/api/star/__init__.py
astrbot/api/util/__init__.py
astrbot/builtin_stars/astrbot/long_term_memory.py
astrbot/builtin_stars/astrbot/main.py
astrbot/builtin_stars/astrbot/metadata.yaml
astrbot/builtin_stars/astrbot/process_llm_request.py
astrbot/builtin_stars/builtin_commands/main.py
astrbot/builtin_stars/builtin_commands/metadata.yaml
astrbot/builtin_stars/builtin_commands/commands/__init__.py
astrbot/builtin_stars/builtin_commands/commands/admin.py
astrbot/builtin_stars/builtin_commands/commands/alter_cmd.py
astrbot/builtin_stars/builtin_commands/commands/conversation.py
astrbot/builtin_stars/builtin_commands/commands/help.py
astrbot/builtin_stars/builtin_commands/commands/llm.py
astrbot/builtin_stars/builtin_commands/commands/persona.py
astrbot/builtin_stars/builtin_commands/commands/plugin.py
astrbot/builtin_stars/builtin_commands/commands/provider.py
astrbot/builtin_stars/builtin_commands/commands/setunset.py
astrbot/builtin_stars/builtin_commands/commands/sid.py
astrbot/builtin_stars/builtin_commands/commands/t2i.py
astrbot/builtin_stars/builtin_commands/commands/tts.py
astrbot/builtin_stars/builtin_commands/commands/utils/rst_scene.py
astrbot/builtin_stars/reminder/main.py
astrbot/builtin_stars/reminder/metadata.yaml
astrbot/builtin_stars/session_controller/main.py
astrbot/builtin_stars/session_controller/metadata.yaml
astrbot/builtin_stars/web_searcher/main.py
astrbot/builtin_stars/web_searcher/metadata.yaml
astrbot/builtin_stars/web_searcher/engines/__init__.py
astrbot/builtin_stars/web_searcher/engines/bing.py
astrbot/builtin_stars/web_searcher/engines/sogo.py
astrbot/cli/__init__.py
astrbot/cli/__main__.py
astrbot/cli/commands/__init__.py
astrbot/cli/commands/cmd_conf.py
astrbot/cli/commands/cmd_init.py
astrbot-4.13.2.dist-info/METADATA
astrbot-4.13.2.dist-info/WHEEL
astrbot-4.13.2.dist-info/entry_points.txt
astrbot-4.13.2.dist-info/licenses/LICENSE
astrbot-4.13.2.dist-info/RECORD
