Metadata-Version: 2.4
Name: AstrBot
Version: 4.13.2
Summary: Easy-to-use multi-platform LLM chatbot and development framework
License-File: LICENSE
Keywords: Astrbot,Astrbot Module,Astrbot Plugin
Requires-Python: >=3.10
Requires-Dist: aiocqhttp>=1.4.4
Requires-Dist: aiodocker>=0.24.0
Requires-Dist: aiofiles>=25.1.0
Requires-Dist: aiohttp>=3.11.18
Requires-Dist: aiosqlite>=0.21.0
Requires-Dist: anthropic>=0.51.0
Requires-Dist: apscheduler>=3.11.0
Requires-Dist: audioop-lts; python_full_version >= '3.13'
Requires-Dist: beautifulsoup4>=4.13.4
Requires-Dist: certifi>=2025.4.26
Requires-Dist: chardet~=5.1.0
Requires-Dist: click>=8.2.1
Requires-Dist: colorlog>=6.9.0
Requires-Dist: cryptography>=44.0.3
Requires-Dist: dashscope>=1.23.2
Requires-Dist: defusedxml>=0.7.1
Requires-Dist: deprecated>=1.2.18
Requires-Dist: dingtalk-stream>=0.22.1
Requires-Dist: docstring-parser>=0.16
Requires-Dist: faiss-cpu==1.10.0
Requires-Dist: filelock>=3.18.0
Requires-Dist: google-genai>=1.56.0
Requires-Dist: jieba>=0.42.1
Requires-Dist: lark-oapi>=1.4.15
Requires-Dist: lxml-html-clean>=0.4.2
Requires-Dist: markitdown-no-magika[docx,xls,xlsx]>=0.1.2
Requires-Dist: mcp>=1.8.0
Requires-Dist: openai>=1.78.0
Requires-Dist: ormsgpack>=1.9.1
Requires-Dist: pillow>=11.2.1
Requires-Dist: pip>=25.1.1
Requires-Dist: psutil<7.2.0,>=5.8.0
Requires-Dist: py-cord>=2.6.1
Requires-Dist: pydantic~=2.10.3
Requires-Dist: pydub>=0.25.1
Requires-Dist: pyjwt>=2.10.1
Requires-Dist: pypdf>=6.1.1
Requires-Dist: python-telegram-bot>=22.0
Requires-Dist: qq-botpy>=1.2.1
Requires-Dist: quart>=0.20.0
Requires-Dist: rank-bm25>=0.2.2
Requires-Dist: readability-lxml>=0.8.4.1
Requires-Dist: shipyard-python-sdk>=0.2.4
Requires-Dist: silk-python>=0.2.6
Requires-Dist: slack-sdk>=3.35.0
Requires-Dist: sqlalchemy[asyncio]>=2.0.41
Requires-Dist: sqlmodel>=0.0.24
Requires-Dist: telegramify-markdown>=0.5.1
Requires-Dist: tenacity>=9.1.2
Requires-Dist: watchfiles>=1.0.5
Requires-Dist: websockets>=15.0.1
Requires-Dist: wechatpy>=1.8.18
Requires-Dist: xinference-client
